{
  "location": "park",
  "level": "b1",
  "items": {
    "vocabulary": [
      {
        "id": "voc_park_b1_W11_001",
        "word": "Bank",
        "article": "die",
        "plural": "Bänke",
        "pronunciation": "디 방크",
        "meaning": "벤치",
        "example": "Wir haben uns auf eine Bank gesetzt und die Sonne genossen.",
        "example_translation": "우리는 벤치에 앉아서 햇볕을 즐겼습니다.",
        "example_pronunciation": "비어 하벤 운스 아우프 아이네 방크 게제츠트 운트 디 존네 게노센.",
        "tags": [
          "Nomen",
          "Park",
          "B1",
          "Möbel"
        ],
        "week": "W11"
      },
      {
        "id": "voc_park_b1_W11_002",
        "word": "Baum",
        "article": "der",
        "plural": "Bäume",
        "pronunciation": "데어 바움",
        "meaning": "나무",
        "example": "Im Park stehen viele alte Bäume.",
        "example_translation": "공원에는 많은 오래된 나무들이 있습니다.",
        "example_pronunciation": "임 파크 슈테엔 필레 알테 보위메.",
        "tags": [
          "Nomen",
          "Park",
          "Natur",
          "B1"
        ],
        "week": "W11"
      },
      {
        "id": "voc_park_b1_W11_003",
        "word": "Wiese",
        "article": "die",
        "plural": "Wiesen",
        "pronunciation": "디 비제",
        "meaning": "잔디밭, 초원",
        "example": "Kinder spielen auf der Wiese Fußball.",
        "example_translation": "아이들이 잔디밭에서 축구를 합니다.",
        "example_pronunciation": "킨더 슈필렌 아우프 데어 비제 푸스발.",
        "tags": [
          "Nomen",
          "Park",
          "Natur",
          "B1"
        ],
        "week": "W11"
      },
      {
        "id": "voc_park_b1_W11_004",
        "word": "genießen",
        "article": "null",
        "plural": "null",
        "pronunciation": "게니센",
        "meaning": "즐기다",
        "example": "Ich genieße die frische Luft im Park.",
        "example_translation": "저는 공원의 신선한 공기를 즐깁니다.",
        "example_pronunciation": "이히 게니세 디 프리쉐 루프트 임 파크.",
        "tags": [
          "Verb",
          "Park",
          "Gefühl",
          "B1"
        ],
        "week": "W11"
      },
      {
        "id": "voc_park_b1_W11_005",
        "word": "Spielplatz",
        "article": "der",
        "plural": "Spielplätze",
        "pronunciation": "데어 슈필플라츠",
        "meaning": "놀이터",
        "example": "Viele Familien besuchen den Spielplatz am Wochenende.",
        "example_translation": "많은 가족들이 주말에 놀이터를 방문합니다.",
        "example_pronunciation": "필레 파밀리엔 베주헨 덴 슈필플라츠 암 보헨엔데.",
        "tags": [
          "Nomen",
          "Park",
          "Kinder",
          "B1"
        ],
        "week": "W11"
      }
    ],
    "grammar": [
      {
        "id": "gram_park_b1_W11_001",
        "type": "fill_blank",
        "topic": "Adjektivendungen (bestimmter Artikel, Dativ Plural)",
        "topic_explanation": "Adjektive, die nach einem bestimmten Artikel (im Dativ) und vor einem Pluralnomen stehen, erhalten in der Regel die Endung '-en'.",
        "question": "Im Park entspannen wir unter den _______ Bäumen.",
        "question_translation": "In the park, we relax under the ______ trees.",
        "options": [
          "großes",
          "große",
          "großer",
          "großen"
        ],
        "answer": "großen",
        "explanation": "Das Bezugswort 'Bäumen' ist Plural und steht nach der Präposition 'unter', die hier mit Dativ verwendet wird ('unter den Bäumen'). Nach dem bestimmten Artikel 'den' (Dativ Plural) erhält das Adjektiv 'groß' die Endung '-en'.",
        "related_table": [],
        "week": "W11"
      },
      {
        "id": "gram_park_b1_W11_002",
        "type": "conjugation_table",
        "topic": "Konjunktiv II (Präteritum) von Modalverben",
        "topic_explanation": "Der Konjunktiv II wird verwendet, um Wünsche, Ratschläge, hypothetische Situationen oder höfliche Bitten auszudrücken. Bei Modalverben wie 'können' wird er oft durch die Präteritumform mit Umlaut gebildet.",
        "question": "Ich wünschte, ich _______ länger im Park bleiben.",
        "question_translation": "I wish I ______ stay longer in the park.",
        "options": [],
        "answer": "könnte",
        "explanation": "Für den Konjunktiv II des Modalverbs 'können' im Präteritum wird die Form 'könnte' verwendet. Die Form für die 1. Person Singular ('ich') ist 'könnte'.",
        "related_table": [
          {
            "pronoun": "ich",
            "form": "könnte"
          },
          {
            "pronoun": "du",
            "form": "könntest"
          },
          {
            "pronoun": "er/sie/es",
            "form": "könnte"
          },
          {
            "pronoun": "wir",
            "form": "könnten"
          },
          {
            "pronoun": "ihr",
            "form": "könntet"
          },
          {
            "pronoun": "sie/Sie",
            "form": "könnten"
          }
        ],
        "week": "W11"
      },
      {
        "id": "gram_park_b1_W11_003",
        "type": "fill_blank",
        "topic": "Relativsätze (Dativ)",
        "topic_explanation": "Relativpronomen leiten Relativsätze ein und passen sich im Genus (Geschlecht) und Numerus (Zahl) an das Bezugswort im Hauptsatz an. Der Kasus (Fall) des Relativpronomens richtet sich nach seiner Funktion im Relativsatz.",
        "question": "Der Mann, _______ wir im Park begegnet sind, arbeitet als Gärtner.",
        "question_translation": "The man, ______ we met in the park, works as a gardener.",
        "options": [
          "den",
          "der",
          "dem",
          "dessen"
        ],
        "answer": "dem",
        "explanation": "Das Bezugswort 'Der Mann' ist Maskulin Singular. Im Relativsatz verlangt das Verb 'begegnen' immer den Dativ (jemandem begegnen). Daher ist das korrekte Relativpronomen im Dativ Maskulin Singular 'dem'.",
        "related_table": [],
        "week": "W11"
      }
    ],
    "conversation": [
      {
        "id": "conv_park_b1_W11_001",
        "situation": "Zwei Freunde treffen sich zufällig im Park und unterhalten sich über ihre Pläne für den Nachmittag.",
        "situation_icon": "🌳",
        "dialogue": [
          {
            "role": "Max",
            "text": "Hallo Lisa! Was machst du denn hier?",
            "pronunciation": "[ˈhalo ˈliːza! vas maχst duː dɛn hiːɐ?]",
            "translation": "Hi Lisa! What are you doing here?",
            "isQuestion": false
          },
          {
            "role": "Lisa",
            "text": "Hallo Max! Ich wollte nur ein bisschen spazieren gehen und die Sonne genießen. Und du?",
            "pronunciation": "[ˈhalo maks! ɪç vɔltə nuːɐ aɪn bɪsçən ʃpaˈtsiːʁən ɡeːən ʊnt diː zɔnə ɡəˈniːsn̩. ʊnt duː?]",
            "translation": "Hi Max! I just wanted to take a little walk and enjoy the sun. And you?",
            "isQuestion": false
          },
          {
            "role": "Max",
            "text": "Ich überlege noch. Vielleicht lese ich ein Buch oder gehe joggen.",
            "pronunciation": "[ɪç yːbɐˈleːɡə nɔχ. filaɪçt leːzə ɪç aɪn buːχ oːdɐ ɡeːə ˈjɔɡn̩.]",
            "translation": "I'm still thinking. Maybe I'll read a book or go jogging.",
            "isQuestion": false
          },
          {
            "role": "Lisa",
            "text": "Ah, verstehe. Ich überlege auch, was ich jetzt mache.",
            "pronunciation": "[aː, fɛɐˈʃteːə. ɪç yːbɐˈleːɡə aʊχ, vas ɪç jɛtst maχə.]",
            "translation": "Ah, I see. I'm also thinking about what to do now.",
            "isQuestion": false
          },
          {
            "role": "Max",
            "text": "Was hältst du davon, wenn wir zusammen einen Kaffee trinken gehen?",
            "pronunciation": "[vas hɛltst duː daˈfɔn, vɛn viːɐ tsuˈzamən aɪnən ˈkafeː ˈtrɪŋkn̩ ɡeːən?]",
            "translation": "What do you think if we go for a coffee together?",
            "isQuestion": true
          }
        ],
        "choices": [
          {
            "text": "Das ist eine super Idee! Ich hätte Lust auf einen Kaffee.",
            "pronunciation": "[das ɪst aɪnə ˈzuːpɐ ɪˈdeː! ɪç hɛtə lʊst aʊf aɪnən ˈkafeː.]",
            "translation": "That's a great idea! I'd fancy a coffee."
          },
          {
            "text": "Ich habe keine Zeit, ich muss jetzt gehen.",
            "pronunciation": "[ɪç haːbə ˈkaɪnə tsaɪt, ɪç mʊs jɛtst ɡeːən.]",
            "translation": "I don't have time, I have to go now."
          },
          {
            "text": "Ich trinke lieber Tee.",
            "pronunciation": "[ɪç ˈtrɪŋkə ˈliːbɐ teː.]",
            "translation": "I prefer to drink tea."
          }
        ],
        "answer": "Das ist eine super Idee! Ich hätte Lust auf einen Kaffee.",
        "explanation": "Max schlägt vor, zusammen Kaffee trinken zu gehen. Die beste positive Antwort auf einen Vorschlag ist, die Idee zu bejahen und eventuell Interesse zu zeigen. Die Antwort \"Ich hätte Lust auf einen Kaffee\" drückt dies passend aus.",
        "grammar_point": "Vorschläge machen mit \"Was hältst du davon, wenn...\" (Subjunktiv II für Vorschläge), positive und negative Reaktionen auf Vorschläge.",
        "week": "W11"
      },
      {
        "id": "conv_park_b1_W11_002",
        "situation": "Eine Touristin fragt einen Einheimischen im Park nach dem Weg zu einem bekannten Denkmal.",
        "situation_icon": "🗺️",
        "dialogue": [
          {
            "role": "Tourist",
            "text": "Entschuldigen Sie, könnten Sie mir vielleicht helfen?",
            "pronunciation": "[ɛntˈʃʊldɪɡn̩ ziː, ˈkœntn̩ ziː miːɐ filaɪçt ˈhɛlfn̩?]",
            "translation": "Excuse me, could you perhaps help me?",
            "isQuestion": false
          },
          {
            "role": "Einheimischer",
            "text": "Ja, gerne. Was kann ich für Sie tun?",
            "pronunciation": "[jaː, ˈɡɛʁnə. vas kan ɪç fyːɐ ziː tuːn?]",
            "translation": "Yes, gladly. What can I do for you?",
            "isQuestion": false
          },
          {
            "role": "Tourist",
            "text": "Ich suche das Schiller-Denkmal. Ist das weit von hier?",
            "pronunciation": "[ɪç zuːxə das ˈʃɪlɐˌdɛŋkmaːl. ɪst das vaɪt fɔn hiːɐ?]",
            "translation": "I'm looking for the Schiller Monument. Is it far from here?",
            "isQuestion": false
          },
          {
            "role": "Einheimischer",
            "text": "Nein, gar nicht. Sie müssen einfach diesem Weg folgen, dann sehen Sie es schon.",
            "pronunciation": "[naɪn, ɡaːɐ nɪçt. ziː mʏsn̩ ˈaɪnfax ˈdiːzəm veːk ˈfɔlɡn̩, dan ˈzeːən ziː ɛs ʃoːn.]",
            "translation": "No, not at all. You just have to follow this path, then you'll see it.",
            "isQuestion": false
          },
          {
            "role": "Tourist",
            "text": "Könnten Sie das bitte noch einmal wiederholen, aber etwas langsamer?",
            "pronunciation": "[ˈkœntn̩ ziː das bɪtə nɔχ aɪnmaːl viːdɐˈhoːln̩, abɐ ɛtvas ˈlaŋzamɐ?]",
            "translation": "Could you please repeat that one more time, but a bit slower?",
            "isQuestion": true
          }
        ],
        "choices": [
          {
            "text": "Ja, kein Problem. Also, Sie gehen hier geradeaus...",
            "pronunciation": "[jaː, kaɪn proˈbleːm. ˈalzoː, ziː ɡeːən hiːɐ ɡəˈraːdəaʊs...]",
            "translation": "Yes, no problem. So, you go straight here..."
          },
          {
            "text": "Warum haben Sie nicht besser aufgepasst?",
            "pronunciation": "[vaˈʁʊm ˈhaːbn̩ ziː nɪçt ˈbɛsɐ aʊfɡəpast?]",
            "translation": "Why didn't you pay better attention?"
          },
          {
            "text": "Ich habe es Ihnen doch schon gesagt.",
            "pronunciation": "[ɪç haːbə ɛs ˈiːnən dɔχ ʃoːn ɡəˈzaːkt.]",
            "translation": "I already told you."
          }
        ],
        "answer": "Ja, kein Problem. Also, Sie gehen hier geradeaus...",
        "explanation": "Die Touristin bittet höflich um eine Wiederholung der Wegbeschreibung in einem langsameren Tempo. Eine hilfsbereite Antwort ist es, dem Wunsch nachzukommen und die Erklärung freundlich zu wiederholen.",
        "grammar_point": "Höfliche Bitten (\"Könnten Sie...?\" + Infinitiv), Verständnisfragen (\"noch einmal wiederholen\"), Wegbeschreibungen geben (Imperativ, Präpositionen).",
        "week": "W11"
      }
    ],
    "expressions": [
      {
        "id": "expr_park_b1_W11_001",
        "phrase": "Lass uns im Park ein Picknick machen!",
        "pronunciation": "라스 운스 임 파크 아인 피크닉 마헨!",
        "meaning": "우리 공원에서 피크닉 하자!",
        "usage": "Das Wetter ist heute so schön. Lass uns im Park ein Picknick machen!",
        "alternatives": [
          {
            "phrase": "Wollen wir im Park picknicken gehen?",
            "pronunciation": "볼렌 비어 임 파크 피크니켄 게헨?",
            "nuance": "조금 더 격식 있거나, 질문 형태"
          },
          {
            "phrase": "Wie wäre es mit einem Picknick im Park?",
            "pronunciation": "비 베어러 에스 밋 아이넴 피크닉 임 파크?",
            "nuance": "제안을 부드럽게 던지는 표현"
          }
        ],
        "responses": [
          {
            "text": "Ja, super Idee! Ich packe schon mal den Korb.",
            "pronunciation": "야, 수퍼 이데! 이히 파케 숀 말 덴 코어프.",
            "translation": "응, 좋은 생각이야! 내가 벌써 바구니 챙길게."
          },
          {
            "text": "Klar, wann sollen wir uns treffen?",
            "pronunciation": "클라, 반 졸렌 비어 운스 트레펜?",
            "translation": "좋아, 언제 만날까?"
          },
          {
            "text": "Oh nein, ich habe leider keine Zeit heute.",
            "pronunciation": "오 나인, 이히 하베 라이더 카이네 차이트 호이테.",
            "translation": "아 안돼, 오늘 아쉽게도 시간이 없어."
          }
        ],
        "week": "W11"
      },
      {
        "id": "expr_park_b1_W11_002",
        "phrase": "Entschuldigen Sie, wo ist hier der nächste Spielplatz?",
        "pronunciation": "엔트슐디겐 지, 보 이스트 히어 데어 넥스테 슈필플라츠?",
        "meaning": "실례합니다, 여기서 가장 가까운 놀이터는 어디인가요?",
        "usage": "Mit meinen Kindern möchte ich auf den Spielplatz. Entschuldigen Sie, wo ist hier der nächste Spielplatz?",
        "alternatives": [
          {
            "phrase": "Könnten Sie mir bitte sagen, wo ich einen Spielplatz finde?",
            "pronunciation": "쾨넨 지 미어 비테 자겐, 보 이히 아이넨 슈필플라츠 핀데?",
            "nuance": "더 정중하고 직접적인 질문"
          },
          {
            "phrase": "Gibt es hier in der Nähe einen Spielplatz?",
            "pronunciation": "깁트 에스 히어 인 데어 내헤 아이넨 슈필플라츠?",
            "nuance": "주변에 있는지 묻는 더 일반적인 질문"
          }
        ],
        "responses": [
          {
            "text": "Gehen Sie einfach geradeaus, dann sehen Sie ihn auf der linken Seite.",
            "pronunciation": "게헨 지 아인파흐 게라데아우스, 단 제헨 지 인 아우프 데어 링켄 자이테.",
            "translation": "그냥 직진하세요, 그러면 왼쪽에 보일 거예요."
          },
          {
            "text": "Ja, der ist gleich um die Ecke.",
            "pronunciation": "야, 데어 이스트 글라이히 움 디 에케.",
            "translation": "네, 바로 모퉁이를 돌면 있어요."
          },
          {
            "text": "Moment, ich schaue mal auf der Karte.",
            "pronunciation": "모멘트, 이히 샤우에 말 아우프 데어 카르테.",
            "translation": "잠시만요, 제가 지도에서 찾아볼게요."
          }
        ],
        "week": "W11"
      },
      {
        "id": "expr_park_b1_W11_003",
        "phrase": "Dieser Park ist ein wunderbarer Ort, um sich zu entspannen.",
        "pronunciation": "디저 파크 이스트 아인 분더바러 오르트, 움 지히 추 엔트슈판넨.",
        "meaning": "이 공원은 휴식을 취하기에 아주 좋은 장소예요.",
        "usage": "Nach einer langen Arbeitswoche besuche ich oft diesen Park. Er ist ein wunderbarer Ort, um sich zu entspannen.",
        "alternatives": [
          {
            "phrase": "Ich finde, dieser Park ist perfekt zum Entspannen.",
            "pronunciation": "이히 핀데, 디저 파크 이스트 페어펙트 춤 엔트슈판넨.",
            "nuance": "개인의 의견을 더 강조하는 표현"
          },
          {
            "phrase": "Man kann sich hier im Park sehr gut erholen.",
            "pronunciation": "만 칸 지히 히어 임 파크 제어 굿 에어홀렌.",
            "nuance": "더 넓은 의미의 '회복하다, 쉬다'라는 뉘앙스"
          }
        ],
        "responses": [
          {
            "text": "Das stimmt, die Ruhe hier ist wirklich wohltuend.",
            "pronunciation": "다스 슈팀트, 디 루헤 히어 이스트 비어클리히 볼투엔트.",
            "translation": "맞아요, 여기의 고요함이 정말 평온해요."
          },
          {
            "text": "Absolut! Ich komme auch gerne hierher, um dem Alltag zu entfliehen.",
            "pronunciation": "압솔루트! 이히 코메 아우흐 게르네 히어헤어, 움 뎀 알탁 추 엔트플리헨.",
            "translation": "전적으로 동감해요! 저도 일상에서 벗어나려고 여기 자주 와요."
          },
          {
            "text": "Ja, aber manchmal ist es mir zu voll.",
            "pronunciation": "야, 아버 만히말 이스트 에스 미어 추 폴.",
            "translation": "네, 하지만 가끔은 너무 붐벼요."
          }
        ],
        "week": "W11"
      }
    ]
  },
  "lastUpdated": "W11"
}